benchmarks/algorithms.py
benchmarks/core.py
benchmarks/generators.py
docs/source/conf.py
examples/advanced/plot_colormaps_colorbars.py
examples/advanced/plot_labels.py
examples/basic/plot_simple_hypergraph.py
examples/basic/plot_simple_hypergraph_hull.py
examples/basic/plot_simple_hypergraph_multilayer.py
examples/basic/plot_simple_hypergraph_outline.py
examples/basic/plot_simple_simplicial_complex.py
examples/layouts/plot_barycenter_spring_layout.py
examples/layouts/plot_simple_graph.py
examples/layouts/plot_spiral_layout.py
examples/stats/plot_color_stat.py
logo/logo.pdf
logo/logo.png
logo/logo.svg
logo/logo_tight.png
logo/logo_white.png
logo/logo_white.svg
logo/logo_white_tight.png
logo/x.png
logo/x.svg
logo/x_tight.png
requirements/README.md
requirements/benchmark.txt
requirements/default.txt
requirements/developer.txt
requirements/docs.txt
requirements/release.txt
requirements/test.txt
requirements/tutorial.txt
tests/conftest.py
tests/algorithms/test_assortativity.py
tests/algorithms/test_centrality.py
tests/algorithms/test_clustering.py
tests/algorithms/test_connected.py
tests/algorithms/test_properties.py
tests/algorithms/test_shortest_path.py
tests/algorithms/test_simpliciality.py
tests/communities/test_spectral.py
tests/convert/test_bipartite_edges.py
tests/convert/test_bipartite_graph.py
tests/convert/test_encapsulation_dag.py
tests/convert/test_graph.py
tests/convert/test_hif_dict.py
tests/convert/test_higher_order_network.py
tests/convert/test_hyperedges.py
tests/convert/test_hypergraph_dict.py
tests/convert/test_incidence.py
tests/convert/test_k_skeleton.py
tests/convert/test_line_graph.py
tests/convert/test_pandas.py
tests/core/test_dihypergraph.py
tests/core/test_globalviews.py
tests/core/test_hypergraph.py
tests/core/test_simplicialcomplex.py
tests/core/test_views.py
tests/drawing/test_draw.py
tests/drawing/test_draw_utils.py
tests/drawing/test_layout.py
tests/dynamics/test_synchronization.py
tests/generators/test_classic.py
xgi-0.10.dist-info/licenses/LICENSE.md
xgi-0.10.dist-info/METADATA
xgi-0.10.dist-info/WHEEL
xgi-0.10.dist-info/top_level.txt
xgi-0.10.dist-info/RECORD
